hudutils/__init__.py
hudutils/hudutils.py
hudutils-0.7.dist-info/LICENSE
hudutils-0.7.dist-info/METADATA
hudutils-0.7.dist-info/WHEEL
hudutils-0.7.dist-info/top_level.txt
hudutils-0.7.dist-info/RECORD
