Metadata-Version: 2.1
Name: hudutils
Version: 0.7
Summary: Huds regularly used utilities 
Home-page: https://github.com/huddaannaa/hudutils
Author: Hud Daannaa
Author-email: hdaannaa@gmail.com
License: MIT
Platform: UNKNOWN
Classifier: Development Status :: 3 - Alpha
Classifier: Intended Audience :: Developers
Classifier: License :: OSI Approved :: MIT License
Classifier: Programming Language :: Python :: 3
Classifier: Programming Language :: Python :: 3.7
Classifier: Programming Language :: Python :: 3.8
Classifier: Programming Language :: Python :: 3.9
Classifier: Programming Language :: Python :: 3.10
License-File: LICENSE
